{
  "date": "2025-06-14",
  "changes": [
    {
      "fileName": ".activity-logs\\log-2025-06-14T20-11-57-186Z.json",
      "timestamp": "2025-06-14T20:11:57.281Z",
      "changeType": "created",
      "linesChanged": 17,
      "fileType": "json"
    },
    {
      "fileName": "src\\pages\\Index.tsx",
      "timestamp": "2025-06-14T20:11:59.393Z",
      "changeType": "modified",
      "linesChanged": 177,
      "fileType": "tsx"
    }
  ],
  "totalChanges": 2,
  "startTime": "2025-06-14T20:11:57.193Z",
  "endTime": "2025-06-14T20:11:59.393Z",
  "projectName": "c:\\Users\\prave\\projects\\trails clone\\Resilience-AI-main",
  "branchName": "main"
}