{
  "date": "2025-06-16",
  "changes": [
    {
      "fileName": "README.md",
      "timestamp": "2025-06-16T10:33:28.980Z",
      "changeType": "modified",
      "linesChanged": 107,
      "fileType": "md"
    },
    {
      "fileName": "README.md",
      "timestamp": "2025-06-16T10:33:30.241Z",
      "changeType": "modified",
      "linesChanged": 107,
      "fileType": "md"
    }
  ],
  "totalChanges": 2,
  "startTime": "2025-06-16T10:33:28.867Z",
  "endTime": "2025-06-16T10:33:30.241Z",
  "projectName": "c:\\Users\\prave\\projects\\trails clone\\Resilience-AI-main",
  "branchName": "main"
}